{
	"configurations" : 
	[
		{
			"directories" : 
			[
				{
					"build" : ".",
					"jsonFile" : "directory-.-Debug-d0094a50bb2071803777.json",
					"minimumCMakeVersion" : 
					{
						"string" : "3.28"
					},
					"projectIndex" : 0,
					"source" : ".",
					"targetIndexes" : 
					[
						0,
						1,
						2,
						3,
						4,
						5,
						6,
						7,
						8,
						9,
						10,
						11
					]
				}
			],
			"name" : "Debug",
			"projects" : 
			[
				{
					"directoryIndexes" : 
					[
						0
					],
					"name" : "Test4",
					"targetIndexes" : 
					[
						0,
						1,
						2,
						3,
						4,
						5,
						6,
						7,
						8,
						9,
						10,
						11
					]
				}
			],
			"targets" : 
			[
				{
					"directoryIndex" : 0,
					"id" : "Test4::@6890427a1f51a3e7e1df",
					"jsonFile" : "target-Test4-Debug-381d88fe7e8aa5120e91.json",
					"name" : "Test4",
					"projectIndex" : 0
				},
				{
					"directoryIndex" : 0,
					"id" : "test1::@6890427a1f51a3e7e1df",
					"jsonFile" : "target-test1-Debug-cc710338da91c011cfa2.json",
					"name" : "test1",
					"projectIndex" : 0
				},
				{
					"directoryIndex" : 0,
					"id" : "test10::@6890427a1f51a3e7e1df",
					"jsonFile" : "target-test10-Debug-364de534b3ca9da95677.json",
					"name" : "test10",
					"projectIndex" : 0
				},
				{
					"directoryIndex" : 0,
					"id" : "test2::@6890427a1f51a3e7e1df",
					"jsonFile" : "target-test2-Debug-cd571cb08f80170fc735.json",
					"name" : "test2",
					"projectIndex" : 0
				},
				{
					"directoryIndex" : 0,
					"id" : "test3::@6890427a1f51a3e7e1df",
					"jsonFile" : "target-test3-Debug-dfa52bdc3a5710c27ee7.json",
					"name" : "test3",
					"projectIndex" : 0
				},
				{
					"directoryIndex" : 0,
					"id" : "test4::@6890427a1f51a3e7e1df",
					"jsonFile" : "target-test4-Debug-24e0328d887e75324814.json",
					"name" : "test4",
					"projectIndex" : 0
				},
				{
					"directoryIndex" : 0,
					"id" : "test5::@6890427a1f51a3e7e1df",
					"jsonFile" : "target-test5-Debug-723cd80af5bb0e476b3e.json",
					"name" : "test5",
					"projectIndex" : 0
				},
				{
					"directoryIndex" : 0,
					"id" : "test6::@6890427a1f51a3e7e1df",
					"jsonFile" : "target-test6-Debug-61b30f44f52b0edc27e5.json",
					"name" : "test6",
					"projectIndex" : 0
				},
				{
					"directoryIndex" : 0,
					"id" : "test7::@6890427a1f51a3e7e1df",
					"jsonFile" : "target-test7-Debug-ecd864c2503044f008f9.json",
					"name" : "test7",
					"projectIndex" : 0
				},
				{
					"directoryIndex" : 0,
					"id" : "test8::@6890427a1f51a3e7e1df",
					"jsonFile" : "target-test8-Debug-fa0d179b9608a46de55a.json",
					"name" : "test8",
					"projectIndex" : 0
				},
				{
					"directoryIndex" : 0,
					"id" : "test9::@6890427a1f51a3e7e1df",
					"jsonFile" : "target-test9-Debug-32dfe257ae487457cf5d.json",
					"name" : "test9",
					"projectIndex" : 0
				},
				{
					"directoryIndex" : 0,
					"id" : "test_5_23.c::@6890427a1f51a3e7e1df",
					"jsonFile" : "target-test_5_23.c-Debug-874c7a84a4501c19afdf.json",
					"name" : "test_5_23.c",
					"projectIndex" : 0
				}
			]
		}
	],
	"kind" : "codemodel",
	"paths" : 
	{
		"build" : "E:/Programs/CLion/Test4/cmake-build-debug",
		"source" : "E:/Programs/CLion/Test4"
	},
	"version" : 
	{
		"major" : 2,
		"minor" : 6
	}
}
