{
	"configurations" : 
	[
		{
			"directories" : 
			[
				{
					"build" : ".",
					"jsonFile" : "directory-.-Debug-d0094a50bb2071803777.json",
					"minimumCMakeVersion" : 
					{
						"string" : "3.28"
					},
					"projectIndex" : 0,
					"source" : ".",
					"targetIndexes" : 
					[
						0,
						1,
						2,
						3,
						4,
						5,
						6,
						7,
						8
					]
				}
			],
			"name" : "Debug",
			"projects" : 
			[
				{
					"directoryIndexes" : 
					[
						0
					],
					"name" : "Test4",
					"targetIndexes" : 
					[
						0,
						1,
						2,
						3,
						4,
						5,
						6,
						7,
						8
					]
				}
			],
			"targets" : 
			[
				{
					"directoryIndex" : 0,
					"id" : "Test4::@6890427a1f51a3e7e1df",
					"jsonFile" : "target-Test4-Debug-381d88fe7e8aa5120e91.json",
					"name" : "Test4",
					"projectIndex" : 0
				},
				{
					"directoryIndex" : 0,
					"id" : "test1::@6890427a1f51a3e7e1df",
					"jsonFile" : "target-test1-Debug-f74676e19f45e7acc50a.json",
					"name" : "test1",
					"projectIndex" : 0
				},
				{
					"directoryIndex" : 0,
					"id" : "test2::@6890427a1f51a3e7e1df",
					"jsonFile" : "target-test2-Debug-ca6b546a3e37002bbb92.json",
					"name" : "test2",
					"projectIndex" : 0
				},
				{
					"directoryIndex" : 0,
					"id" : "test3::@6890427a1f51a3e7e1df",
					"jsonFile" : "target-test3-Debug-359bbae38e1adb3df945.json",
					"name" : "test3",
					"projectIndex" : 0
				},
				{
					"directoryIndex" : 0,
					"id" : "test4::@6890427a1f51a3e7e1df",
					"jsonFile" : "target-test4-Debug-a5ddc34ad740c07ba58d.json",
					"name" : "test4",
					"projectIndex" : 0
				},
				{
					"directoryIndex" : 0,
					"id" : "test5::@6890427a1f51a3e7e1df",
					"jsonFile" : "target-test5-Debug-2c1ddef243a03733271c.json",
					"name" : "test5",
					"projectIndex" : 0
				},
				{
					"directoryIndex" : 0,
					"id" : "test6::@6890427a1f51a3e7e1df",
					"jsonFile" : "target-test6-Debug-d6f6a3563625223eca4a.json",
					"name" : "test6",
					"projectIndex" : 0
				},
				{
					"directoryIndex" : 0,
					"id" : "test7::@6890427a1f51a3e7e1df",
					"jsonFile" : "target-test7-Debug-5c15623324d435463884.json",
					"name" : "test7",
					"projectIndex" : 0
				},
				{
					"directoryIndex" : 0,
					"id" : "test_5_23.c::@6890427a1f51a3e7e1df",
					"jsonFile" : "target-test_5_23.c-Debug-1eb46aaa877e4641a576.json",
					"name" : "test_5_23.c",
					"projectIndex" : 0
				}
			]
		}
	],
	"kind" : "codemodel",
	"paths" : 
	{
		"build" : "E:/Programs/CLion/Test4/cmake-build-debug",
		"source" : "E:/Programs/CLion/Test4"
	},
	"version" : 
	{
		"major" : 2,
		"minor" : 6
	}
}
